Metadata-Version: 2.1
Name: torchpruner
Version: 0.0.5
Summary: Python library to perform pruning of pytorch neural networks
Author: Ashhadul Islam, Samir Brahim Belhaouari
License-File: LICENSE.rst
